[
  {
    "fullName": "esti",
    "age": "50",
    "email": "esti@eklaw.co.il",
    "password": "esti100"
  },
  {
    "fullName": "adir",
    "age": "34",
    "email": "adir.avraham@gmail.com",
    "password": "ghghgh"
  },
  {
    "fullName": "saraf",
    "age": "33",
    "email": "sara@eklaw.com",
    "password": "34fssw"
  },
  {
    "fullName": "sadf",
    "age": "3333",
    "email": "wwerwer",
    "password": "33443"
  },
  {
    "fullName": "nitzan-avraham",
    "age": 20,
    "email": "nitzan@gmail.com",
    "password": "1111"
  },
  {
    "fullName": "nitzan-avraham",
    "age": 21,
    "email": "nitzan1@gmail.com",
    "password": "1111"
  },
  {
    "fullName": "nitzan-avraham",
    "age": 21,
    "email": "nitzan2@gmail.com",
    "password": "1111"
  },
  {
    "fullName": "nitzan-avraham",
    "age": 21,
    "email": "nitzan3@gmail.com",
    "password": "1111"
  },
  {
    "fullName": "nitzan-avraham",
    "age": 21,
    "email": "nitzan4@gmail.com",
    "password": "1111"
  }
]